my_demo_cli/__init__.py
my_demo_cli/cli.py
my_demo_cli-0.1.0.dist-info/METADATA
my_demo_cli-0.1.0.dist-info/WHEEL
my_demo_cli-0.1.0.dist-info/entry_points.txt
my_demo_cli-0.1.0.dist-info/RECORD
